{
  "extensionVersion": "1.5.2",
  "fileName": "c:\\Users\\kytka\\source\\learning\\FPGA_gowin\\rv32im\\sim\\bus_xbar_atomic_tb.fst",
  "markerTime": 245000,
  "altMarkerTime": null,
  "displayTimeUnit": "ps",
  "selectedSignal": {
    "name": "bus_xbar_atomic_tb.wb_m[0].clk",
    "msb": -1,
    "lsb": -1
  },
  "zoomRatio": 0.0016,
  "scrollLeft": 31190,
  "displayedSignals": [
    {
      "dataType": "signal-group",
      "groupName": "M0",
      "collapseState": 2,
      "children": [
        {
          "dataType": "netlist-variable",
          "netlistId": 87,
          "name": "bus_xbar_atomic_tb.wb_m[0].ack",
          "numberFormat": "binary",
          "colorIndex": 0,
          "rowHeight": 1,
          "verticalScale": 1,
          "nameType": "fullPath",
          "customName": "ack",
          "renderType": "binary",
          "valueLinkCommand": ""
        },
        {
          "dataType": "netlist-variable",
          "netlistId": 80,
          "name": "bus_xbar_atomic_tb.wb_m[0].adr",
          "numberFormat": "hexadecimal",
          "colorIndex": 3,
          "rowHeight": 1,
          "verticalScale": 1,
          "nameType": "fullPath",
          "customName": "adr",
          "renderType": "multiBit",
          "valueLinkCommand": ""
        },
        {
          "dataType": "netlist-variable",
          "netlistId": 78,
          "name": "bus_xbar_atomic_tb.wb_m[0].clk",
          "numberFormat": "binary",
          "colorIndex": 0,
          "rowHeight": 1,
          "verticalScale": 1,
          "nameType": "fullPath",
          "customName": "clk",
          "renderType": "binary",
          "valueLinkCommand": ""
        },
        {
          "dataType": "netlist-variable",
          "netlistId": 84,
          "name": "bus_xbar_atomic_tb.wb_m[0].cyc",
          "numberFormat": "binary",
          "colorIndex": 0,
          "rowHeight": 1,
          "verticalScale": 1,
          "nameType": "fullPath",
          "customName": "cyc",
          "renderType": "binary",
          "valueLinkCommand": ""
        },
        {
          "dataType": "netlist-variable",
          "netlistId": 88,
          "name": "bus_xbar_atomic_tb.wb_m[0].err",
          "numberFormat": "binary",
          "colorIndex": 0,
          "rowHeight": 1,
          "verticalScale": 1,
          "nameType": "fullPath",
          "customName": "err",
          "renderType": "binary",
          "valueLinkCommand": ""
        },
        {
          "dataType": "netlist-variable",
          "netlistId": 81,
          "name": "bus_xbar_atomic_tb.wb_m[0].mtos",
          "numberFormat": "hexadecimal",
          "colorIndex": 3,
          "rowHeight": 1,
          "verticalScale": 1,
          "nameType": "fullPath",
          "customName": "mtos",
          "renderType": "multiBit",
          "valueLinkCommand": ""
        },
        {
          "dataType": "netlist-variable",
          "netlistId": 79,
          "name": "bus_xbar_atomic_tb.wb_m[0].rst",
          "numberFormat": "binary",
          "colorIndex": 0,
          "rowHeight": 1,
          "verticalScale": 1,
          "nameType": "fullPath",
          "customName": "rst",
          "renderType": "binary",
          "valueLinkCommand": ""
        },
        {
          "dataType": "netlist-variable",
          "netlistId": 89,
          "name": "bus_xbar_atomic_tb.wb_m[0].rty",
          "numberFormat": "binary",
          "colorIndex": 0,
          "rowHeight": 1,
          "verticalScale": 1,
          "nameType": "fullPath",
          "customName": "rty",
          "renderType": "binary",
          "valueLinkCommand": ""
        },
        {
          "dataType": "netlist-variable",
          "netlistId": 82,
          "name": "bus_xbar_atomic_tb.wb_m[0].sel",
          "numberFormat": "hexadecimal",
          "colorIndex": 3,
          "rowHeight": 1,
          "verticalScale": 1,
          "nameType": "fullPath",
          "customName": "sel",
          "renderType": "multiBit",
          "valueLinkCommand": ""
        },
        {
          "dataType": "netlist-variable",
          "netlistId": 85,
          "name": "bus_xbar_atomic_tb.wb_m[0].stb",
          "numberFormat": "binary",
          "colorIndex": 0,
          "rowHeight": 1,
          "verticalScale": 1,
          "nameType": "fullPath",
          "customName": "stb",
          "renderType": "binary",
          "valueLinkCommand": ""
        },
        {
          "dataType": "netlist-variable",
          "netlistId": 86,
          "name": "bus_xbar_atomic_tb.wb_m[0].stom",
          "numberFormat": "hexadecimal",
          "colorIndex": 3,
          "rowHeight": 1,
          "verticalScale": 1,
          "nameType": "fullPath",
          "customName": "stom",
          "renderType": "multiBit",
          "valueLinkCommand": ""
        },
        {
          "dataType": "netlist-variable",
          "netlistId": 83,
          "name": "bus_xbar_atomic_tb.wb_m[0].we",
          "numberFormat": "binary",
          "colorIndex": 0,
          "rowHeight": 1,
          "verticalScale": 1,
          "nameType": "fullPath",
          "customName": "we",
          "renderType": "binary",
          "valueLinkCommand": ""
        }
      ]
    },
    {
      "dataType": "signal-group",
      "groupName": "M1",
      "collapseState": 2,
      "children": [
        {
          "dataType": "netlist-variable",
          "netlistId": 99,
          "name": "bus_xbar_atomic_tb.wb_m[1].ack",
          "numberFormat": "binary",
          "colorIndex": 0,
          "rowHeight": 1,
          "verticalScale": 1,
          "nameType": "fullPath",
          "customName": "ack",
          "renderType": "binary",
          "valueLinkCommand": ""
        },
        {
          "dataType": "netlist-variable",
          "netlistId": 92,
          "name": "bus_xbar_atomic_tb.wb_m[1].adr",
          "numberFormat": "hexadecimal",
          "colorIndex": 3,
          "rowHeight": 1,
          "verticalScale": 1,
          "nameType": "fullPath",
          "customName": "adr",
          "renderType": "multiBit",
          "valueLinkCommand": ""
        },
        {
          "dataType": "netlist-variable",
          "netlistId": 90,
          "name": "bus_xbar_atomic_tb.wb_m[1].clk",
          "numberFormat": "binary",
          "colorIndex": 0,
          "rowHeight": 1,
          "verticalScale": 1,
          "nameType": "fullPath",
          "customName": "clk",
          "renderType": "binary",
          "valueLinkCommand": ""
        },
        {
          "dataType": "netlist-variable",
          "netlistId": 96,
          "name": "bus_xbar_atomic_tb.wb_m[1].cyc",
          "numberFormat": "binary",
          "colorIndex": 0,
          "rowHeight": 1,
          "verticalScale": 1,
          "nameType": "fullPath",
          "customName": "cyc",
          "renderType": "binary",
          "valueLinkCommand": ""
        },
        {
          "dataType": "netlist-variable",
          "netlistId": 100,
          "name": "bus_xbar_atomic_tb.wb_m[1].err",
          "numberFormat": "binary",
          "colorIndex": 0,
          "rowHeight": 1,
          "verticalScale": 1,
          "nameType": "fullPath",
          "customName": "err",
          "renderType": "binary",
          "valueLinkCommand": ""
        },
        {
          "dataType": "netlist-variable",
          "netlistId": 93,
          "name": "bus_xbar_atomic_tb.wb_m[1].mtos",
          "numberFormat": "hexadecimal",
          "colorIndex": 3,
          "rowHeight": 1,
          "verticalScale": 1,
          "nameType": "fullPath",
          "customName": "mtos",
          "renderType": "multiBit",
          "valueLinkCommand": ""
        },
        {
          "dataType": "netlist-variable",
          "netlistId": 91,
          "name": "bus_xbar_atomic_tb.wb_m[1].rst",
          "numberFormat": "binary",
          "colorIndex": 0,
          "rowHeight": 1,
          "verticalScale": 1,
          "nameType": "fullPath",
          "customName": "rst",
          "renderType": "binary",
          "valueLinkCommand": ""
        },
        {
          "dataType": "netlist-variable",
          "netlistId": 101,
          "name": "bus_xbar_atomic_tb.wb_m[1].rty",
          "numberFormat": "binary",
          "colorIndex": 0,
          "rowHeight": 1,
          "verticalScale": 1,
          "nameType": "fullPath",
          "customName": "rty",
          "renderType": "binary",
          "valueLinkCommand": ""
        },
        {
          "dataType": "netlist-variable",
          "netlistId": 94,
          "name": "bus_xbar_atomic_tb.wb_m[1].sel",
          "numberFormat": "hexadecimal",
          "colorIndex": 3,
          "rowHeight": 1,
          "verticalScale": 1,
          "nameType": "fullPath",
          "customName": "sel",
          "renderType": "multiBit",
          "valueLinkCommand": ""
        },
        {
          "dataType": "netlist-variable",
          "netlistId": 97,
          "name": "bus_xbar_atomic_tb.wb_m[1].stb",
          "numberFormat": "binary",
          "colorIndex": 0,
          "rowHeight": 1,
          "verticalScale": 1,
          "nameType": "fullPath",
          "customName": "stb",
          "renderType": "binary",
          "valueLinkCommand": ""
        },
        {
          "dataType": "netlist-variable",
          "netlistId": 98,
          "name": "bus_xbar_atomic_tb.wb_m[1].stom",
          "numberFormat": "hexadecimal",
          "colorIndex": 3,
          "rowHeight": 1,
          "verticalScale": 1,
          "nameType": "fullPath",
          "customName": "stom",
          "renderType": "multiBit",
          "valueLinkCommand": ""
        },
        {
          "dataType": "netlist-variable",
          "netlistId": 95,
          "name": "bus_xbar_atomic_tb.wb_m[1].we",
          "numberFormat": "binary",
          "colorIndex": 0,
          "rowHeight": 1,
          "verticalScale": 1,
          "nameType": "fullPath",
          "customName": "we",
          "renderType": "binary",
          "valueLinkCommand": ""
        }
      ]
    },
    {
      "dataType": "signal-group",
      "groupName": "M2",
      "collapseState": 2,
      "children": [
        {
          "dataType": "netlist-variable",
          "netlistId": 111,
          "name": "bus_xbar_atomic_tb.wb_m[2].ack",
          "numberFormat": "binary",
          "colorIndex": 0,
          "rowHeight": 1,
          "verticalScale": 1,
          "nameType": "fullPath",
          "customName": "ack",
          "renderType": "binary",
          "valueLinkCommand": ""
        },
        {
          "dataType": "netlist-variable",
          "netlistId": 104,
          "name": "bus_xbar_atomic_tb.wb_m[2].adr",
          "numberFormat": "hexadecimal",
          "colorIndex": 3,
          "rowHeight": 1,
          "verticalScale": 1,
          "nameType": "fullPath",
          "customName": "adr",
          "renderType": "multiBit",
          "valueLinkCommand": ""
        },
        {
          "dataType": "netlist-variable",
          "netlistId": 102,
          "name": "bus_xbar_atomic_tb.wb_m[2].clk",
          "numberFormat": "binary",
          "colorIndex": 0,
          "rowHeight": 1,
          "verticalScale": 1,
          "nameType": "fullPath",
          "customName": "clk",
          "renderType": "binary",
          "valueLinkCommand": ""
        },
        {
          "dataType": "netlist-variable",
          "netlistId": 108,
          "name": "bus_xbar_atomic_tb.wb_m[2].cyc",
          "numberFormat": "binary",
          "colorIndex": 0,
          "rowHeight": 1,
          "verticalScale": 1,
          "nameType": "fullPath",
          "customName": "cyc",
          "renderType": "binary",
          "valueLinkCommand": ""
        },
        {
          "dataType": "netlist-variable",
          "netlistId": 112,
          "name": "bus_xbar_atomic_tb.wb_m[2].err",
          "numberFormat": "binary",
          "colorIndex": 0,
          "rowHeight": 1,
          "verticalScale": 1,
          "nameType": "fullPath",
          "customName": "err",
          "renderType": "binary",
          "valueLinkCommand": ""
        },
        {
          "dataType": "netlist-variable",
          "netlistId": 105,
          "name": "bus_xbar_atomic_tb.wb_m[2].mtos",
          "numberFormat": "hexadecimal",
          "colorIndex": 3,
          "rowHeight": 1,
          "verticalScale": 1,
          "nameType": "fullPath",
          "customName": "mtos",
          "renderType": "multiBit",
          "valueLinkCommand": ""
        },
        {
          "dataType": "netlist-variable",
          "netlistId": 103,
          "name": "bus_xbar_atomic_tb.wb_m[2].rst",
          "numberFormat": "binary",
          "colorIndex": 0,
          "rowHeight": 1,
          "verticalScale": 1,
          "nameType": "fullPath",
          "customName": "rst",
          "renderType": "binary",
          "valueLinkCommand": ""
        },
        {
          "dataType": "netlist-variable",
          "netlistId": 113,
          "name": "bus_xbar_atomic_tb.wb_m[2].rty",
          "numberFormat": "binary",
          "colorIndex": 0,
          "rowHeight": 1,
          "verticalScale": 1,
          "nameType": "fullPath",
          "customName": "rty",
          "renderType": "binary",
          "valueLinkCommand": ""
        },
        {
          "dataType": "netlist-variable",
          "netlistId": 106,
          "name": "bus_xbar_atomic_tb.wb_m[2].sel",
          "numberFormat": "hexadecimal",
          "colorIndex": 3,
          "rowHeight": 1,
          "verticalScale": 1,
          "nameType": "fullPath",
          "customName": "sel",
          "renderType": "multiBit",
          "valueLinkCommand": ""
        },
        {
          "dataType": "netlist-variable",
          "netlistId": 109,
          "name": "bus_xbar_atomic_tb.wb_m[2].stb",
          "numberFormat": "binary",
          "colorIndex": 0,
          "rowHeight": 1,
          "verticalScale": 1,
          "nameType": "fullPath",
          "customName": "stb",
          "renderType": "binary",
          "valueLinkCommand": ""
        },
        {
          "dataType": "netlist-variable",
          "netlistId": 110,
          "name": "bus_xbar_atomic_tb.wb_m[2].stom",
          "numberFormat": "hexadecimal",
          "colorIndex": 3,
          "rowHeight": 1,
          "verticalScale": 1,
          "nameType": "fullPath",
          "customName": "stom",
          "renderType": "multiBit",
          "valueLinkCommand": ""
        },
        {
          "dataType": "netlist-variable",
          "netlistId": 107,
          "name": "bus_xbar_atomic_tb.wb_m[2].we",
          "numberFormat": "binary",
          "colorIndex": 0,
          "rowHeight": 1,
          "verticalScale": 1,
          "nameType": "fullPath",
          "customName": "we",
          "renderType": "binary",
          "valueLinkCommand": ""
        }
      ]
    },
    {
      "dataType": "signal-group",
      "groupName": "M3",
      "collapseState": 1,
      "children": [
        {
          "dataType": "netlist-variable",
          "netlistId": 123,
          "name": "bus_xbar_atomic_tb.wb_m[3].ack",
          "numberFormat": "binary",
          "colorIndex": 0,
          "rowHeight": 1,
          "verticalScale": 1,
          "nameType": "fullPath",
          "customName": "ack",
          "renderType": "binary",
          "valueLinkCommand": ""
        },
        {
          "dataType": "netlist-variable",
          "netlistId": 116,
          "name": "bus_xbar_atomic_tb.wb_m[3].adr",
          "numberFormat": "hexadecimal",
          "colorIndex": 3,
          "rowHeight": 1,
          "verticalScale": 1,
          "nameType": "fullPath",
          "customName": "adr",
          "renderType": "multiBit",
          "valueLinkCommand": ""
        },
        {
          "dataType": "netlist-variable",
          "netlistId": 114,
          "name": "bus_xbar_atomic_tb.wb_m[3].clk",
          "numberFormat": "binary",
          "colorIndex": 0,
          "rowHeight": 1,
          "verticalScale": 1,
          "nameType": "fullPath",
          "customName": "clk",
          "renderType": "binary",
          "valueLinkCommand": ""
        },
        {
          "dataType": "netlist-variable",
          "netlistId": 120,
          "name": "bus_xbar_atomic_tb.wb_m[3].cyc",
          "numberFormat": "binary",
          "colorIndex": 0,
          "rowHeight": 1,
          "verticalScale": 1,
          "nameType": "fullPath",
          "customName": "cyc",
          "renderType": "binary",
          "valueLinkCommand": ""
        },
        {
          "dataType": "netlist-variable",
          "netlistId": 124,
          "name": "bus_xbar_atomic_tb.wb_m[3].err",
          "numberFormat": "binary",
          "colorIndex": 0,
          "rowHeight": 1,
          "verticalScale": 1,
          "nameType": "fullPath",
          "customName": "err",
          "renderType": "binary",
          "valueLinkCommand": ""
        },
        {
          "dataType": "netlist-variable",
          "netlistId": 117,
          "name": "bus_xbar_atomic_tb.wb_m[3].mtos",
          "numberFormat": "hexadecimal",
          "colorIndex": 3,
          "rowHeight": 1,
          "verticalScale": 1,
          "nameType": "fullPath",
          "customName": "mtos",
          "renderType": "multiBit",
          "valueLinkCommand": ""
        },
        {
          "dataType": "netlist-variable",
          "netlistId": 115,
          "name": "bus_xbar_atomic_tb.wb_m[3].rst",
          "numberFormat": "binary",
          "colorIndex": 0,
          "rowHeight": 1,
          "verticalScale": 1,
          "nameType": "fullPath",
          "customName": "rst",
          "renderType": "binary",
          "valueLinkCommand": ""
        },
        {
          "dataType": "netlist-variable",
          "netlistId": 125,
          "name": "bus_xbar_atomic_tb.wb_m[3].rty",
          "numberFormat": "binary",
          "colorIndex": 0,
          "rowHeight": 1,
          "verticalScale": 1,
          "nameType": "fullPath",
          "customName": "rty",
          "renderType": "binary",
          "valueLinkCommand": ""
        },
        {
          "dataType": "netlist-variable",
          "netlistId": 118,
          "name": "bus_xbar_atomic_tb.wb_m[3].sel",
          "numberFormat": "hexadecimal",
          "colorIndex": 3,
          "rowHeight": 1,
          "verticalScale": 1,
          "nameType": "fullPath",
          "customName": "sel",
          "renderType": "multiBit",
          "valueLinkCommand": ""
        },
        {
          "dataType": "netlist-variable",
          "netlistId": 121,
          "name": "bus_xbar_atomic_tb.wb_m[3].stb",
          "numberFormat": "binary",
          "colorIndex": 0,
          "rowHeight": 1,
          "verticalScale": 1,
          "nameType": "fullPath",
          "customName": "stb",
          "renderType": "binary",
          "valueLinkCommand": ""
        },
        {
          "dataType": "netlist-variable",
          "netlistId": 122,
          "name": "bus_xbar_atomic_tb.wb_m[3].stom",
          "numberFormat": "hexadecimal",
          "colorIndex": 3,
          "rowHeight": 1,
          "verticalScale": 1,
          "nameType": "fullPath",
          "customName": "stom",
          "renderType": "multiBit",
          "valueLinkCommand": ""
        },
        {
          "dataType": "netlist-variable",
          "netlistId": 119,
          "name": "bus_xbar_atomic_tb.wb_m[3].we",
          "numberFormat": "binary",
          "colorIndex": 0,
          "rowHeight": 1,
          "verticalScale": 1,
          "nameType": "fullPath",
          "customName": "we",
          "renderType": "binary",
          "valueLinkCommand": ""
        }
      ]
    },
    {
      "dataType": "signal-group",
      "groupName": "M4",
      "collapseState": 1,
      "children": [
        {
          "dataType": "netlist-variable",
          "netlistId": 135,
          "name": "bus_xbar_atomic_tb.wb_m[4].ack",
          "numberFormat": "binary",
          "colorIndex": 0,
          "rowHeight": 1,
          "verticalScale": 1,
          "nameType": "fullPath",
          "customName": "ack",
          "renderType": "binary",
          "valueLinkCommand": ""
        },
        {
          "dataType": "netlist-variable",
          "netlistId": 128,
          "name": "bus_xbar_atomic_tb.wb_m[4].adr",
          "numberFormat": "hexadecimal",
          "colorIndex": 3,
          "rowHeight": 1,
          "verticalScale": 1,
          "nameType": "fullPath",
          "customName": "adr",
          "renderType": "multiBit",
          "valueLinkCommand": ""
        },
        {
          "dataType": "netlist-variable",
          "netlistId": 126,
          "name": "bus_xbar_atomic_tb.wb_m[4].clk",
          "numberFormat": "binary",
          "colorIndex": 0,
          "rowHeight": 1,
          "verticalScale": 1,
          "nameType": "fullPath",
          "customName": "clk",
          "renderType": "binary",
          "valueLinkCommand": ""
        },
        {
          "dataType": "netlist-variable",
          "netlistId": 132,
          "name": "bus_xbar_atomic_tb.wb_m[4].cyc",
          "numberFormat": "binary",
          "colorIndex": 0,
          "rowHeight": 1,
          "verticalScale": 1,
          "nameType": "fullPath",
          "customName": "cyc",
          "renderType": "binary",
          "valueLinkCommand": ""
        },
        {
          "dataType": "netlist-variable",
          "netlistId": 136,
          "name": "bus_xbar_atomic_tb.wb_m[4].err",
          "numberFormat": "binary",
          "colorIndex": 0,
          "rowHeight": 1,
          "verticalScale": 1,
          "nameType": "fullPath",
          "customName": "err",
          "renderType": "binary",
          "valueLinkCommand": ""
        },
        {
          "dataType": "netlist-variable",
          "netlistId": 129,
          "name": "bus_xbar_atomic_tb.wb_m[4].mtos",
          "numberFormat": "hexadecimal",
          "colorIndex": 3,
          "rowHeight": 1,
          "verticalScale": 1,
          "nameType": "fullPath",
          "customName": "mtos",
          "renderType": "multiBit",
          "valueLinkCommand": ""
        },
        {
          "dataType": "netlist-variable",
          "netlistId": 127,
          "name": "bus_xbar_atomic_tb.wb_m[4].rst",
          "numberFormat": "binary",
          "colorIndex": 0,
          "rowHeight": 1,
          "verticalScale": 1,
          "nameType": "fullPath",
          "customName": "rst",
          "renderType": "binary",
          "valueLinkCommand": ""
        },
        {
          "dataType": "netlist-variable",
          "netlistId": 137,
          "name": "bus_xbar_atomic_tb.wb_m[4].rty",
          "numberFormat": "binary",
          "colorIndex": 0,
          "rowHeight": 1,
          "verticalScale": 1,
          "nameType": "fullPath",
          "customName": "rty",
          "renderType": "binary",
          "valueLinkCommand": ""
        },
        {
          "dataType": "netlist-variable",
          "netlistId": 130,
          "name": "bus_xbar_atomic_tb.wb_m[4].sel",
          "numberFormat": "hexadecimal",
          "colorIndex": 3,
          "rowHeight": 1,
          "verticalScale": 1,
          "nameType": "fullPath",
          "customName": "sel",
          "renderType": "multiBit",
          "valueLinkCommand": ""
        },
        {
          "dataType": "netlist-variable",
          "netlistId": 133,
          "name": "bus_xbar_atomic_tb.wb_m[4].stb",
          "numberFormat": "binary",
          "colorIndex": 0,
          "rowHeight": 1,
          "verticalScale": 1,
          "nameType": "fullPath",
          "customName": "stb",
          "renderType": "binary",
          "valueLinkCommand": ""
        },
        {
          "dataType": "netlist-variable",
          "netlistId": 134,
          "name": "bus_xbar_atomic_tb.wb_m[4].stom",
          "numberFormat": "hexadecimal",
          "colorIndex": 3,
          "rowHeight": 1,
          "verticalScale": 1,
          "nameType": "fullPath",
          "customName": "stom",
          "renderType": "multiBit",
          "valueLinkCommand": ""
        },
        {
          "dataType": "netlist-variable",
          "netlistId": 131,
          "name": "bus_xbar_atomic_tb.wb_m[4].we",
          "numberFormat": "binary",
          "colorIndex": 0,
          "rowHeight": 1,
          "verticalScale": 1,
          "nameType": "fullPath",
          "customName": "we",
          "renderType": "binary",
          "valueLinkCommand": ""
        }
      ]
    },
    {
      "dataType": "signal-group",
      "groupName": "S0",
      "collapseState": 2,
      "children": [
        {
          "dataType": "netlist-variable",
          "netlistId": 15,
          "name": "bus_xbar_atomic_tb.dut.s_bus[0].ack",
          "numberFormat": "binary",
          "colorIndex": 0,
          "rowHeight": 1,
          "verticalScale": 1,
          "nameType": "fullPath",
          "customName": "ack",
          "renderType": "binary",
          "valueLinkCommand": ""
        },
        {
          "dataType": "netlist-variable",
          "netlistId": 8,
          "name": "bus_xbar_atomic_tb.dut.s_bus[0].adr",
          "numberFormat": "hexadecimal",
          "colorIndex": 3,
          "rowHeight": 1,
          "verticalScale": 1,
          "nameType": "fullPath",
          "customName": "adr",
          "renderType": "multiBit",
          "valueLinkCommand": ""
        },
        {
          "dataType": "netlist-variable",
          "netlistId": 6,
          "name": "bus_xbar_atomic_tb.dut.s_bus[0].clk",
          "numberFormat": "binary",
          "colorIndex": 0,
          "rowHeight": 1,
          "verticalScale": 1,
          "nameType": "fullPath",
          "customName": "clk",
          "renderType": "binary",
          "valueLinkCommand": ""
        },
        {
          "dataType": "netlist-variable",
          "netlistId": 12,
          "name": "bus_xbar_atomic_tb.dut.s_bus[0].cyc",
          "numberFormat": "binary",
          "colorIndex": 0,
          "rowHeight": 1,
          "verticalScale": 1,
          "nameType": "fullPath",
          "customName": "cyc",
          "renderType": "binary",
          "valueLinkCommand": ""
        },
        {
          "dataType": "netlist-variable",
          "netlistId": 16,
          "name": "bus_xbar_atomic_tb.dut.s_bus[0].err",
          "numberFormat": "binary",
          "colorIndex": 0,
          "rowHeight": 1,
          "verticalScale": 1,
          "nameType": "fullPath",
          "customName": "err",
          "renderType": "binary",
          "valueLinkCommand": ""
        },
        {
          "dataType": "netlist-variable",
          "netlistId": 9,
          "name": "bus_xbar_atomic_tb.dut.s_bus[0].mtos",
          "numberFormat": "hexadecimal",
          "colorIndex": 3,
          "rowHeight": 1,
          "verticalScale": 1,
          "nameType": "fullPath",
          "customName": "mtos",
          "renderType": "multiBit",
          "valueLinkCommand": ""
        },
        {
          "dataType": "netlist-variable",
          "netlistId": 7,
          "name": "bus_xbar_atomic_tb.dut.s_bus[0].rst",
          "numberFormat": "binary",
          "colorIndex": 0,
          "rowHeight": 1,
          "verticalScale": 1,
          "nameType": "fullPath",
          "customName": "rst",
          "renderType": "binary",
          "valueLinkCommand": ""
        },
        {
          "dataType": "netlist-variable",
          "netlistId": 17,
          "name": "bus_xbar_atomic_tb.dut.s_bus[0].rty",
          "numberFormat": "binary",
          "colorIndex": 0,
          "rowHeight": 1,
          "verticalScale": 1,
          "nameType": "fullPath",
          "customName": "rty",
          "renderType": "binary",
          "valueLinkCommand": ""
        },
        {
          "dataType": "netlist-variable",
          "netlistId": 10,
          "name": "bus_xbar_atomic_tb.dut.s_bus[0].sel",
          "numberFormat": "hexadecimal",
          "colorIndex": 3,
          "rowHeight": 1,
          "verticalScale": 1,
          "nameType": "fullPath",
          "customName": "sel",
          "renderType": "multiBit",
          "valueLinkCommand": ""
        },
        {
          "dataType": "netlist-variable",
          "netlistId": 13,
          "name": "bus_xbar_atomic_tb.dut.s_bus[0].stb",
          "numberFormat": "binary",
          "colorIndex": 0,
          "rowHeight": 1,
          "verticalScale": 1,
          "nameType": "fullPath",
          "customName": "stb",
          "renderType": "binary",
          "valueLinkCommand": ""
        },
        {
          "dataType": "netlist-variable",
          "netlistId": 14,
          "name": "bus_xbar_atomic_tb.dut.s_bus[0].stom",
          "numberFormat": "hexadecimal",
          "colorIndex": 3,
          "rowHeight": 1,
          "verticalScale": 1,
          "nameType": "fullPath",
          "customName": "stom",
          "renderType": "multiBit",
          "valueLinkCommand": ""
        },
        {
          "dataType": "netlist-variable",
          "netlistId": 11,
          "name": "bus_xbar_atomic_tb.dut.s_bus[0].we",
          "numberFormat": "binary",
          "colorIndex": 0,
          "rowHeight": 1,
          "verticalScale": 1,
          "nameType": "fullPath",
          "customName": "we",
          "renderType": "binary",
          "valueLinkCommand": ""
        }
      ]
    }
  ]
}